docs/source/conf.py
ecmwf/download_cams_all.py
ecmwf/download_cams_cds.py
ecmwf/download_cams_cds_day.py
exe/__init__.py
exe/acix_grs_proc.py
exe/call_amalthee.py
exe/call_subprocess.py
exe/call_subprocess_multiproc.py
exe/download_list.py
exe/grs_call.py
exe/grs_from_list.py
exe/grs_proc_sites.py
exe/grs_tiles_cnes.py
exe/grs_tiles_cnes_v2.py
exe/grs_validation.py
exe/launcher.py
exe/procutils.py
exe/test_mp.py
exe/list/construct_list.py
grs/__init__.py
grs/acutils.py
grs/auxdata.py
grs/cams.py
grs/config.yml
grs/config_template.yml
grs/config_template_cnes.yml
grs/grs_process.py
grs/mask.py
grs/output.py
grs/product.py
grs/run.py
grs/data/__init__.py
grs/data/aux/__init__.py
grs/data/aux/mean_rglint_small_angles_vza_le_12_sza_le_60.txt
grs/data/aux/rayleigh_bodhaine.txt
grs/data/lut/__init__.py
grs/data/lut/gases/__init__.py
grs/data/lut/gases/lut_abs_opt_thickness_normalized.nc
grs/data/lut/gases/water_vapor_transmittance.nc
issues/cams/test_cams.py
issues/cams/test_cams_cds.py
issues/dem/__init__.py
issues/dem/check_dem_availability.py
issues/dem/dem_slope_aspect.py
issues/flags/test_flags.py
issues/format/formats_and_extensions.py
issues/format/test_snappy_writer.py
issues/grs_test/grs_test.py
issues/grs_test/grs_test_ v2.py
issues/lut_interpol/lut_interpol_test.py
issues/multiproc/multiproc_snappy.py
issues/resampling/test2_snappy_dispose.py
issues/resampling/test2_snappy_resampling.py
issues/resampling/test_snappy_landsat_op.py
issues/resampling/test_snappy_resampling.py
issues/resampling/test_subprocess.py
issues/s2sampler/test2_snappy_resampling.py
issues/s2sampler/test_pythonS2resample.py
issues/timelag/plot_toa_refl_timelag.py
test/grs_test_ v2.py
test/grs_test_ v2_cnes.py
GRSprocessor-2.1.6.dist-info/LICENSE
GRSprocessor-2.1.6.dist-info/METADATA
GRSprocessor-2.1.6.dist-info/WHEEL
GRSprocessor-2.1.6.dist-info/entry_points.txt
GRSprocessor-2.1.6.dist-info/top_level.txt
GRSprocessor-2.1.6.dist-info/RECORD
