Metadata-Version: 2.1
Name: GRSprocessor
Version: 2.1.6
Summary: GRS processor for atmospheric correction of high-spatial resolution and multispectral satellite images
Author-email: Tristan Harmel <tristan.harmel@gmail.com>
License: Apache License
Project-URL: Homepage, https://github.com/Tristanovsk/grs
Project-URL: Documentation, https://grs.readthedocs.io
Keywords: Sentinel-2,Landsat-8,Landsat-9,atmospheric correction,EO satellite
Classifier: License :: OSI Approved :: Apache Software License
Classifier: Programming Language :: Python
Classifier: Programming Language :: Python :: 3
Requires-Python: >=3.9
License-File: LICENSE
Provides-Extra: dev
Requires-Dist: black ; extra == 'dev'
Requires-Dist: bumpver ; extra == 'dev'
Requires-Dist: isort ; extra == 'dev'
Requires-Dist: pip-tools ; extra == 'dev'
Requires-Dist: pytest ; extra == 'dev'
